{"_format":"ethers-rs-sol-cache-3","paths":{"artifacts":"out","build_infos":"out/build-info","sources":"contracts","tests":"test","scripts":"script","libraries":["lib"]},"files":{"contracts/src/SimulatorV1.sol":{"lastModificationDate":1703759392387,"contentHash":"9d4899d876414a201b33a4e9e68a81e5","sourceName":"contracts/src/SimulatorV1.sol","solcConfig":{"settings":{"optimizer":{"enabled":true,"runs":200},"metadata":{"useLiteralContent":false,"bytecodeHash":"ipfs","appendCBOR":true},"outputSelection":{"*":{"":["ast"],"*":["abi","evm.bytecode","evm.deployedBytecode","evm.methodIdentifiers","metadata"]}},"evmVersion":"paris","libraries":{}}},"imports":["contracts/src/protocols/curve/ICurvePool.sol","contracts/src/protocols/uniswap/IQuoterV2.sol","contracts/src/protocols/uniswap/IUniswapV2Pair.sol","contracts/src/protocols/uniswap/UniswapV2Library.sol"],"versionRequirement":"^0.8.9","artifacts":{"SimulatorV1":{"0.8.23+commit.f704f362.Darwin.appleclang":"SimulatorV1.sol/SimulatorV1.json"}}},"contracts/src/WhackAMoleBotV1.sol":{"lastModificationDate":1703694801662,"contentHash":"229185aa82bd6a08439cdfebdd16ec88","sourceName":"contracts/src/WhackAMoleBotV1.sol","solcConfig":{"settings":{"optimizer":{"enabled":true,"runs":200},"metadata":{"useLiteralContent":false,"bytecodeHash":"ipfs","appendCBOR":true},"outputSelection":{"*":{"":["ast"],"*":["abi","evm.bytecode","evm.deployedBytecode","evm.methodIdentifiers","metadata"]}},"evmVersion":"paris","libraries":{}}},"imports":["contracts/src/protocols/uniswap/IUniswapV2Router.sol","contracts/src/protocols/uniswap/IUniswapV3SwapRouter.sol","openzeppelin-contracts/contracts/token/ERC20/IERC20.sol","openzeppelin-contracts/contracts/token/ERC20/extensions/IERC20Permit.sol","openzeppelin-contracts/contracts/token/ERC20/utils/SafeERC20.sol","openzeppelin-contracts/contracts/utils/Address.sol"],"versionRequirement":"^0.8.9","artifacts":{"WhackAMoleBotV1":{"0.8.23+commit.f704f362.Darwin.appleclang":"WhackAMoleBotV1.sol/WhackAMoleBotV1.json"}}},"contracts/src/lib/SafeTransfer.sol":{"lastModificationDate":1703380646165,"contentHash":"907e08e241f5619622c1ee617164ad37","sourceName":"contracts/src/lib/SafeTransfer.sol","solcConfig":{"settings":{"optimizer":{"enabled":true,"runs":200},"metadata":{"useLiteralContent":false,"bytecodeHash":"ipfs","appendCBOR":true},"outputSelection":{"*":{"":["ast"],"*":["abi","evm.bytecode","evm.deployedBytecode","evm.methodIdentifiers","metadata"]}},"evmVersion":"paris","libraries":{}}},"imports":["contracts/src/protocols/IERC20.sol"],"versionRequirement":"^0.8.9","artifacts":{"SafeTransfer":{"0.8.23+commit.f704f362.Darwin.appleclang":"SafeTransfer.sol/SafeTransfer.json"}}},"contracts/src/protocols/IERC20.sol":{"lastModificationDate":1703380646165,"contentHash":"4c81cd61a312e2873f30e221485de526","sourceName":"contracts/src/protocols/IERC20.sol","solcConfig":{"settings":{"optimizer":{"enabled":true,"runs":200},"metadata":{"useLiteralContent":false,"bytecodeHash":"ipfs","appendCBOR":true},"outputSelection":{"*":{"":["ast"],"*":["abi","evm.bytecode","evm.deployedBytecode","evm.methodIdentifiers","metadata"]}},"evmVersion":"paris","libraries":{}}},"imports":[],"versionRequirement":"^0.8.9","artifacts":{"IERC20":{"0.8.23+commit.f704f362.Darwin.appleclang":"IERC20.sol/IERC20.json"}}},"contracts/src/protocols/IWETH.sol":{"lastModificationDate":1703380646165,"contentHash":"d645ea443187292b3cd2c59b2f01ff13","sourceName":"contracts/src/protocols/IWETH.sol","solcConfig":{"settings":{"optimizer":{"enabled":true,"runs":200},"metadata":{"useLiteralContent":false,"bytecodeHash":"ipfs","appendCBOR":true},"outputSelection":{"*":{"":["ast"],"*":["abi","evm.bytecode","evm.deployedBytecode","evm.methodIdentifiers","metadata"]}},"evmVersion":"paris","libraries":{}}},"imports":["contracts/src/protocols/IERC20.sol"],"versionRequirement":"^0.8.9","artifacts":{"IWETH":{"0.8.23+commit.f704f362.Darwin.appleclang":"IWETH.sol/IWETH.json"}}},"contracts/src/protocols/curve/ICurvePool.sol":{"lastModificationDate":1703380646165,"contentHash":"497e9643ea708ed8bbf11ccffbfd9ada","sourceName":"contracts/src/protocols/curve/ICurvePool.sol","solcConfig":{"settings":{"optimizer":{"enabled":true,"runs":200},"metadata":{"useLiteralContent":false,"bytecodeHash":"ipfs","appendCBOR":true},"outputSelection":{"*":{"":["ast"],"*":["abi","evm.bytecode","evm.deployedBytecode","evm.methodIdentifiers","metadata"]}},"evmVersion":"paris","libraries":{}}},"imports":[],"versionRequirement":"^0.8.9","artifacts":{"ICurvePool":{"0.8.23+commit.f704f362.Darwin.appleclang":"ICurvePool.sol/ICurvePool.json"}}},"contracts/src/protocols/uniswap/IQuoterV2.sol":{"lastModificationDate":1703380646165,"contentHash":"f26a1cdecb5fde306a785807b93afcae","sourceName":"contracts/src/protocols/uniswap/IQuoterV2.sol","solcConfig":{"settings":{"optimizer":{"enabled":true,"runs":200},"metadata":{"useLiteralContent":false,"bytecodeHash":"ipfs","appendCBOR":true},"outputSelection":{"*":{"":["ast"],"*":["abi","evm.bytecode","evm.deployedBytecode","evm.methodIdentifiers","metadata"]}},"evmVersion":"paris","libraries":{}}},"imports":[],"versionRequirement":"^0.8.9","artifacts":{"IQuoterV2":{"0.8.23+commit.f704f362.Darwin.appleclang":"IQuoterV2.sol/IQuoterV2.json"}}},"contracts/src/protocols/uniswap/IUniswapV2Pair.sol":{"lastModificationDate":1703380646165,"contentHash":"1bc3dc9c82015f3de77d16d3e926e6e2","sourceName":"contracts/src/protocols/uniswap/IUniswapV2Pair.sol","solcConfig":{"settings":{"optimizer":{"enabled":true,"runs":200},"metadata":{"useLiteralContent":false,"bytecodeHash":"ipfs","appendCBOR":true},"outputSelection":{"*":{"":["ast"],"*":["abi","evm.bytecode","evm.deployedBytecode","evm.methodIdentifiers","metadata"]}},"evmVersion":"paris","libraries":{}}},"imports":[],"versionRequirement":"^0.8.9","artifacts":{"IUniswapV2Pair":{"0.8.23+commit.f704f362.Darwin.appleclang":"IUniswapV2Pair.sol/IUniswapV2Pair.json"}}},"contracts/src/protocols/uniswap/IUniswapV2Router.sol":{"lastModificationDate":1703380646165,"contentHash":"70af2f1ccc774396cf580352ab9d00e3","sourceName":"contracts/src/protocols/uniswap/IUniswapV2Router.sol","solcConfig":{"settings":{"optimizer":{"enabled":true,"runs":200},"metadata":{"useLiteralContent":false,"bytecodeHash":"ipfs","appendCBOR":true},"outputSelection":{"*":{"":["ast"],"*":["abi","evm.bytecode","evm.deployedBytecode","evm.methodIdentifiers","metadata"]}},"evmVersion":"paris","libraries":{}}},"imports":[],"versionRequirement":"^0.8.9","artifacts":{"IUniswapV2Router":{"0.8.23+commit.f704f362.Darwin.appleclang":"IUniswapV2Router.sol/IUniswapV2Router.json"}}},"contracts/src/protocols/uniswap/IUniswapV3SwapRouter.sol":{"lastModificationDate":1703380646165,"contentHash":"7b23fafeae0bd97d22a86e55772ab845","sourceName":"contracts/src/protocols/uniswap/IUniswapV3SwapRouter.sol","solcConfig":{"settings":{"optimizer":{"enabled":true,"runs":200},"metadata":{"useLiteralContent":false,"bytecodeHash":"ipfs","appendCBOR":true},"outputSelection":{"*":{"":["ast"],"*":["abi","evm.bytecode","evm.deployedBytecode","evm.methodIdentifiers","metadata"]}},"evmVersion":"paris","libraries":{}}},"imports":[],"versionRequirement":"^0.8.9","artifacts":{"ISwapRouter":{"0.8.23+commit.f704f362.Darwin.appleclang":"IUniswapV3SwapRouter.sol/ISwapRouter.json"}}},"contracts/src/protocols/uniswap/UniswapV2Library.sol":{"lastModificationDate":1703694620254,"contentHash":"493c81d9763e08589e81eda461f17f3c","sourceName":"contracts/src/protocols/uniswap/UniswapV2Library.sol","solcConfig":{"settings":{"optimizer":{"enabled":true,"runs":200},"metadata":{"useLiteralContent":false,"bytecodeHash":"ipfs","appendCBOR":true},"outputSelection":{"*":{"":["ast"],"*":["abi","evm.bytecode","evm.deployedBytecode","evm.methodIdentifiers","metadata"]}},"evmVersion":"paris","libraries":{}}},"imports":["contracts/src/protocols/uniswap/IUniswapV2Pair.sol"],"versionRequirement":"^0.8.9","artifacts":{"UniswapV2Library":{"0.8.23+commit.f704f362.Darwin.appleclang":"UniswapV2Library.sol/UniswapV2Library.json"}}},"contracts/test/WhackAMoleBotV1.t.sol":{"lastModificationDate":1703380646166,"contentHash":"8b74b7d0d2c60dc7f86181d0fa6759e2","sourceName":"contracts/test/WhackAMoleBotV1.t.sol","solcConfig":{"settings":{"optimizer":{"enabled":true,"runs":200},"metadata":{"useLiteralContent":false,"bytecodeHash":"ipfs","appendCBOR":true},"outputSelection":{"*":{"":["ast"],"*":["abi","evm.bytecode","evm.deployedBytecode","evm.methodIdentifiers","metadata"]}},"evmVersion":"paris","libraries":{}}},"imports":["contracts/src/SimulatorV1.sol","contracts/src/WhackAMoleBotV1.sol","contracts/src/protocols/curve/ICurvePool.sol","contracts/src/protocols/uniswap/IQuoterV2.sol","contracts/src/protocols/uniswap/IUniswapV2Pair.sol","contracts/src/protocols/uniswap/IUniswapV2Router.sol","contracts/src/protocols/uniswap/IUniswapV3SwapRouter.sol","contracts/src/protocols/uniswap/UniswapV2Library.sol","lib/forge-std/lib/ds-test/src/test.sol","lib/forge-std/src/Base.sol","lib/forge-std/src/StdAssertions.sol","lib/forge-std/src/StdChains.sol","lib/forge-std/src/StdCheats.sol","lib/forge-std/src/StdError.sol","lib/forge-std/src/StdInvariant.sol","lib/forge-std/src/StdJson.sol","lib/forge-std/src/StdMath.sol","lib/forge-std/src/StdStorage.sol","lib/forge-std/src/StdStyle.sol","lib/forge-std/src/StdUtils.sol","lib/forge-std/src/Test.sol","lib/forge-std/src/Vm.sol","lib/forge-std/src/console.sol","lib/forge-std/src/console2.sol","lib/forge-std/src/interfaces/IMulticall3.sol","lib/forge-std/src/mocks/MockERC20.sol","lib/forge-std/src/mocks/MockERC721.sol","lib/forge-std/src/safeconsole.sol","openzeppelin-contracts/contracts/token/ERC20/IERC20.sol","openzeppelin-contracts/contracts/token/ERC20/extensions/IERC20Permit.sol","openzeppelin-contracts/contracts/token/ERC20/utils/SafeERC20.sol","openzeppelin-contracts/contracts/utils/Address.sol"],"versionRequirement":"^0.8.9","artifacts":{"FoundryDemoTest":{"0.8.23+commit.f704f362.Darwin.appleclang":"WhackAMoleBotV1.t.sol/FoundryDemoTest.json"}}},"lib/forge-std/lib/ds-test/src/test.sol":{"lastModificationDate":1703694316586,"contentHash":"9febff9d09f18af5306669dc276c4c43","sourceName":"lib/forge-std/lib/ds-test/src/test.sol","solcConfig":{"settings":{"optimizer":{"enabled":true,"runs":200},"metadata":{"useLiteralContent":false,"bytecodeHash":"ipfs","appendCBOR":true},"outputSelection":{"*":{"":["ast"],"*":["abi","evm.bytecode","evm.deployedBytecode","evm.methodIdentifiers","metadata"]}},"evmVersion":"paris","libraries":{}}},"imports":[],"versionRequirement":">=0.5.0","artifacts":{"DSTest":{"0.8.23+commit.f704f362.Darwin.appleclang":"test.sol/DSTest.json"}}},"lib/forge-std/src/Base.sol":{"lastModificationDate":1703694315475,"contentHash":"ee13c050b1914464f1d3f90cde90204b","sourceName":"lib/forge-std/src/Base.sol","solcConfig":{"settings":{"optimizer":{"enabled":true,"runs":200},"metadata":{"useLiteralContent":false,"bytecodeHash":"ipfs","appendCBOR":true},"outputSelection":{"*":{"":["ast"],"*":["abi","evm.bytecode","evm.deployedBytecode","evm.methodIdentifiers","metadata"]}},"evmVersion":"paris","libraries":{}}},"imports":["lib/forge-std/src/StdStorage.sol","lib/forge-std/src/Vm.sol"],"versionRequirement":">=0.6.2, <0.9.0","artifacts":{"CommonBase":{"0.8.23+commit.f704f362.Darwin.appleclang":"Base.sol/CommonBase.json"},"ScriptBase":{"0.8.23+commit.f704f362.Darwin.appleclang":"Base.sol/ScriptBase.json"},"TestBase":{"0.8.23+commit.f704f362.Darwin.appleclang":"Base.sol/TestBase.json"}}},"lib/forge-std/src/StdAssertions.sol":{"lastModificationDate":1703694315475,"contentHash":"6cc2858240bcd443debbbf075490e325","sourceName":"lib/forge-std/src/StdAssertions.sol","solcConfig":{"settings":{"optimizer":{"enabled":true,"runs":200},"metadata":{"useLiteralContent":false,"bytecodeHash":"ipfs","appendCBOR":true},"outputSelection":{"*":{"":["ast"],"*":["abi","evm.bytecode","evm.deployedBytecode","evm.methodIdentifiers","metadata"]}},"evmVersion":"paris","libraries":{}}},"imports":["lib/forge-std/lib/ds-test/src/test.sol","lib/forge-std/src/StdMath.sol"],"versionRequirement":">=0.6.2, <0.9.0","artifacts":{"StdAssertions":{"0.8.23+commit.f704f362.Darwin.appleclang":"StdAssertions.sol/StdAssertions.json"}}},"lib/forge-std/src/StdChains.sol":{"lastModificationDate":1703694315475,"contentHash":"266a53b71b3a6b9c6c1d7e7763610cb8","sourceName":"lib/forge-std/src/StdChains.sol","solcConfig":{"settings":{"optimizer":{"enabled":true,"runs":200},"metadata":{"useLiteralContent":false,"bytecodeHash":"ipfs","appendCBOR":true},"outputSelection":{"*":{"":["ast"],"*":["abi","evm.bytecode","evm.deployedBytecode","evm.methodIdentifiers","metadata"]}},"evmVersion":"paris","libraries":{}}},"imports":["lib/forge-std/src/Vm.sol"],"versionRequirement":">=0.6.2, <0.9.0","artifacts":{"StdChains":{"0.8.23+commit.f704f362.Darwin.appleclang":"StdChains.sol/StdChains.json"}}},"lib/forge-std/src/StdCheats.sol":{"lastModificationDate":1703694315475,"contentHash":"7922ae0087a21ee3cdb97137be18c06c","sourceName":"lib/forge-std/src/StdCheats.sol","solcConfig":{"settings":{"optimizer":{"enabled":true,"runs":200},"metadata":{"useLiteralContent":false,"bytecodeHash":"ipfs","appendCBOR":true},"outputSelection":{"*":{"":["ast"],"*":["abi","evm.bytecode","evm.deployedBytecode","evm.methodIdentifiers","metadata"]}},"evmVersion":"paris","libraries":{}}},"imports":["lib/forge-std/src/StdStorage.sol","lib/forge-std/src/Vm.sol","lib/forge-std/src/console2.sol"],"versionRequirement":">=0.6.2, <0.9.0","artifacts":{"StdCheats":{"0.8.23+commit.f704f362.Darwin.appleclang":"StdCheats.sol/StdCheats.json"},"StdCheatsSafe":{"0.8.23+commit.f704f362.Darwin.appleclang":"StdCheats.sol/StdCheatsSafe.json"}}},"lib/forge-std/src/StdError.sol":{"lastModificationDate":1703694315475,"contentHash":"64c896e1276a291776e5ea5aecb3870a","sourceName":"lib/forge-std/src/StdError.sol","solcConfig":{"settings":{"optimizer":{"enabled":true,"runs":200},"metadata":{"useLiteralContent":false,"bytecodeHash":"ipfs","appendCBOR":true},"outputSelection":{"*":{"":["ast"],"*":["abi","evm.bytecode","evm.deployedBytecode","evm.methodIdentifiers","metadata"]}},"evmVersion":"paris","libraries":{}}},"imports":[],"versionRequirement":">=0.6.2, <0.9.0","artifacts":{"stdError":{"0.8.23+commit.f704f362.Darwin.appleclang":"StdError.sol/stdError.json"}}},"lib/forge-std/src/StdInvariant.sol":{"lastModificationDate":1703694315476,"contentHash":"0a580d6fac69e9d4b6504f747f3c0c24","sourceName":"lib/forge-std/src/StdInvariant.sol","solcConfig":{"settings":{"optimizer":{"enabled":true,"runs":200},"metadata":{"useLiteralContent":false,"bytecodeHash":"ipfs","appendCBOR":true},"outputSelection":{"*":{"":["ast"],"*":["abi","evm.bytecode","evm.deployedBytecode","evm.methodIdentifiers","metadata"]}},"evmVersion":"paris","libraries":{}}},"imports":[],"versionRequirement":">=0.6.2, <0.9.0","artifacts":{"StdInvariant":{"0.8.23+commit.f704f362.Darwin.appleclang":"StdInvariant.sol/StdInvariant.json"}}},"lib/forge-std/src/StdJson.sol":{"lastModificationDate":1703694315476,"contentHash":"a341308627b7eeab7589534daad58186","sourceName":"lib/forge-std/src/StdJson.sol","solcConfig":{"settings":{"optimizer":{"enabled":true,"runs":200},"metadata":{"useLiteralContent":false,"bytecodeHash":"ipfs","appendCBOR":true},"outputSelection":{"*":{"":["ast"],"*":["abi","evm.bytecode","evm.deployedBytecode","evm.methodIdentifiers","metadata"]}},"evmVersion":"paris","libraries":{}}},"imports":["lib/forge-std/src/Vm.sol"],"versionRequirement":">=0.6.0, <0.9.0","artifacts":{"stdJson":{"0.8.23+commit.f704f362.Darwin.appleclang":"StdJson.sol/stdJson.json"}}},"lib/forge-std/src/StdMath.sol":{"lastModificationDate":1703694315476,"contentHash":"9da8f453eba6bb98f3d75bc6822bfb29","sourceName":"lib/forge-std/src/StdMath.sol","solcConfig":{"settings":{"optimizer":{"enabled":true,"runs":200},"metadata":{"useLiteralContent":false,"bytecodeHash":"ipfs","appendCBOR":true},"outputSelection":{"*":{"":["ast"],"*":["abi","evm.bytecode","evm.deployedBytecode","evm.methodIdentifiers","metadata"]}},"evmVersion":"paris","libraries":{}}},"imports":[],"versionRequirement":">=0.6.2, <0.9.0","artifacts":{"stdMath":{"0.8.23+commit.f704f362.Darwin.appleclang":"StdMath.sol/stdMath.json"}}},"lib/forge-std/src/StdStorage.sol":{"lastModificationDate":1703694315476,"contentHash":"abd6f3379e6e2a7979b18abc21aea0c1","sourceName":"lib/forge-std/src/StdStorage.sol","solcConfig":{"settings":{"optimizer":{"enabled":true,"runs":200},"metadata":{"useLiteralContent":false,"bytecodeHash":"ipfs","appendCBOR":true},"outputSelection":{"*":{"":["ast"],"*":["abi","evm.bytecode","evm.deployedBytecode","evm.methodIdentifiers","metadata"]}},"evmVersion":"paris","libraries":{}}},"imports":["lib/forge-std/src/Vm.sol"],"versionRequirement":">=0.6.2, <0.9.0","artifacts":{"stdStorage":{"0.8.23+commit.f704f362.Darwin.appleclang":"StdStorage.sol/stdStorage.json"},"stdStorageSafe":{"0.8.23+commit.f704f362.Darwin.appleclang":"StdStorage.sol/stdStorageSafe.json"}}},"lib/forge-std/src/StdStyle.sol":{"lastModificationDate":1703694315476,"contentHash":"6281165a12aa639705c691fccefd855e","sourceName":"lib/forge-std/src/StdStyle.sol","solcConfig":{"settings":{"optimizer":{"enabled":true,"runs":200},"metadata":{"useLiteralContent":false,"bytecodeHash":"ipfs","appendCBOR":true},"outputSelection":{"*":{"":["ast"],"*":["abi","evm.bytecode","evm.deployedBytecode","evm.methodIdentifiers","metadata"]}},"evmVersion":"paris","libraries":{}}},"imports":["lib/forge-std/src/Vm.sol"],"versionRequirement":">=0.4.22, <0.9.0","artifacts":{"StdStyle":{"0.8.23+commit.f704f362.Darwin.appleclang":"StdStyle.sol/StdStyle.json"}}},"lib/forge-std/src/StdUtils.sol":{"lastModificationDate":1703694315476,"contentHash":"2ace460f60242ec59c9310db966aee97","sourceName":"lib/forge-std/src/StdUtils.sol","solcConfig":{"settings":{"optimizer":{"enabled":true,"runs":200},"metadata":{"useLiteralContent":false,"bytecodeHash":"ipfs","appendCBOR":true},"outputSelection":{"*":{"":["ast"],"*":["abi","evm.bytecode","evm.deployedBytecode","evm.methodIdentifiers","metadata"]}},"evmVersion":"paris","libraries":{}}},"imports":["lib/forge-std/src/Vm.sol","lib/forge-std/src/interfaces/IMulticall3.sol","lib/forge-std/src/mocks/MockERC20.sol","lib/forge-std/src/mocks/MockERC721.sol"],"versionRequirement":">=0.6.2, <0.9.0","artifacts":{"StdUtils":{"0.8.23+commit.f704f362.Darwin.appleclang":"StdUtils.sol/StdUtils.json"}}},"lib/forge-std/src/Test.sol":{"lastModificationDate":1703694315476,"contentHash":"15866901137b5670eabf31362523bd28","sourceName":"lib/forge-std/src/Test.sol","solcConfig":{"settings":{"optimizer":{"enabled":true,"runs":200},"metadata":{"useLiteralContent":false,"bytecodeHash":"ipfs","appendCBOR":true},"outputSelection":{"*":{"":["ast"],"*":["abi","evm.bytecode","evm.deployedBytecode","evm.methodIdentifiers","metadata"]}},"evmVersion":"paris","libraries":{}}},"imports":["lib/forge-std/lib/ds-test/src/test.sol","lib/forge-std/src/Base.sol","lib/forge-std/src/StdAssertions.sol","lib/forge-std/src/StdChains.sol","lib/forge-std/src/StdCheats.sol","lib/forge-std/src/StdError.sol","lib/forge-std/src/StdInvariant.sol","lib/forge-std/src/StdJson.sol","lib/forge-std/src/StdMath.sol","lib/forge-std/src/StdStorage.sol","lib/forge-std/src/StdStyle.sol","lib/forge-std/src/StdUtils.sol","lib/forge-std/src/Vm.sol","lib/forge-std/src/console.sol","lib/forge-std/src/console2.sol","lib/forge-std/src/interfaces/IMulticall3.sol","lib/forge-std/src/mocks/MockERC20.sol","lib/forge-std/src/mocks/MockERC721.sol","lib/forge-std/src/safeconsole.sol"],"versionRequirement":">=0.6.2, <0.9.0","artifacts":{"Test":{"0.8.23+commit.f704f362.Darwin.appleclang":"Test.sol/Test.json"}}},"lib/forge-std/src/Vm.sol":{"lastModificationDate":1703694316629,"contentHash":"44e160f15058bcfde52b01dbdfeccb95","sourceName":"lib/forge-std/src/Vm.sol","solcConfig":{"settings":{"optimizer":{"enabled":true,"runs":200},"metadata":{"useLiteralContent":false,"bytecodeHash":"ipfs","appendCBOR":true},"outputSelection":{"*":{"":["ast"],"*":["abi","evm.bytecode","evm.deployedBytecode","evm.methodIdentifiers","metadata"]}},"evmVersion":"paris","libraries":{}}},"imports":[],"versionRequirement":">=0.6.2, <0.9.0","artifacts":{"Vm":{"0.8.23+commit.f704f362.Darwin.appleclang":"Vm.sol/Vm.json"},"VmSafe":{"0.8.23+commit.f704f362.Darwin.appleclang":"Vm.sol/VmSafe.json"}}},"lib/forge-std/src/console.sol":{"lastModificationDate":1703694315476,"contentHash":"100b8a33b917da1147740d7ab8b0ded3","sourceName":"lib/forge-std/src/console.sol","solcConfig":{"settings":{"optimizer":{"enabled":true,"runs":200},"metadata":{"useLiteralContent":false,"bytecodeHash":"ipfs","appendCBOR":true},"outputSelection":{"*":{"":["ast"],"*":["abi","evm.bytecode","evm.deployedBytecode","evm.methodIdentifiers","metadata"]}},"evmVersion":"paris","libraries":{}}},"imports":[],"versionRequirement":">=0.4.22, <0.9.0","artifacts":{"console":{"0.8.23+commit.f704f362.Darwin.appleclang":"console.sol/console.json"}}},"lib/forge-std/src/console2.sol":{"lastModificationDate":1703694315477,"contentHash":"491ca717c1915995e78cc361485a3067","sourceName":"lib/forge-std/src/console2.sol","solcConfig":{"settings":{"optimizer":{"enabled":true,"runs":200},"metadata":{"useLiteralContent":false,"bytecodeHash":"ipfs","appendCBOR":true},"outputSelection":{"*":{"":["ast"],"*":["abi","evm.bytecode","evm.deployedBytecode","evm.methodIdentifiers","metadata"]}},"evmVersion":"paris","libraries":{}}},"imports":[],"versionRequirement":">=0.4.22, <0.9.0","artifacts":{"console2":{"0.8.23+commit.f704f362.Darwin.appleclang":"console2.sol/console2.json"}}},"lib/forge-std/src/interfaces/IMulticall3.sol":{"lastModificationDate":1703694315477,"contentHash":"7b131ca1ca32ef6378b7b9ad5488b901","sourceName":"lib/forge-std/src/interfaces/IMulticall3.sol","solcConfig":{"settings":{"optimizer":{"enabled":true,"runs":200},"metadata":{"useLiteralContent":false,"bytecodeHash":"ipfs","appendCBOR":true},"outputSelection":{"*":{"":["ast"],"*":["abi","evm.bytecode","evm.deployedBytecode","evm.methodIdentifiers","metadata"]}},"evmVersion":"paris","libraries":{}}},"imports":[],"versionRequirement":">=0.6.2, <0.9.0","artifacts":{"IMulticall3":{"0.8.23+commit.f704f362.Darwin.appleclang":"IMulticall3.sol/IMulticall3.json"}}},"lib/forge-std/src/mocks/MockERC20.sol":{"lastModificationDate":1703694315477,"contentHash":"9ec848e74c56e40afdd01ac0c873dc3b","sourceName":"lib/forge-std/src/mocks/MockERC20.sol","solcConfig":{"settings":{"optimizer":{"enabled":true,"runs":200},"metadata":{"useLiteralContent":false,"bytecodeHash":"ipfs","appendCBOR":true},"outputSelection":{"*":{"":["ast"],"*":["abi","evm.bytecode","evm.deployedBytecode","evm.methodIdentifiers","metadata"]}},"evmVersion":"paris","libraries":{}}},"imports":[],"versionRequirement":">=0.6.2, <0.9.0","artifacts":{"MockERC20":{"0.8.23+commit.f704f362.Darwin.appleclang":"MockERC20.sol/MockERC20.json"}}},"lib/forge-std/src/mocks/MockERC721.sol":{"lastModificationDate":1703694315478,"contentHash":"b6729ea581dcd9b4238eee9ca4d3bd89","sourceName":"lib/forge-std/src/mocks/MockERC721.sol","solcConfig":{"settings":{"optimizer":{"enabled":true,"runs":200},"metadata":{"useLiteralContent":false,"bytecodeHash":"ipfs","appendCBOR":true},"outputSelection":{"*":{"":["ast"],"*":["abi","evm.bytecode","evm.deployedBytecode","evm.methodIdentifiers","metadata"]}},"evmVersion":"paris","libraries":{}}},"imports":[],"versionRequirement":">=0.6.2, <0.9.0","artifacts":{"IERC721TokenReceiver":{"0.8.23+commit.f704f362.Darwin.appleclang":"MockERC721.sol/IERC721TokenReceiver.json"},"MockERC721":{"0.8.23+commit.f704f362.Darwin.appleclang":"MockERC721.sol/MockERC721.json"}}},"lib/forge-std/src/safeconsole.sol":{"lastModificationDate":1703694315478,"contentHash":"ac3b1bf5a444db5db3656021830258a8","sourceName":"lib/forge-std/src/safeconsole.sol","solcConfig":{"settings":{"optimizer":{"enabled":true,"runs":200},"metadata":{"useLiteralContent":false,"bytecodeHash":"ipfs","appendCBOR":true},"outputSelection":{"*":{"":["ast"],"*":["abi","evm.bytecode","evm.deployedBytecode","evm.methodIdentifiers","metadata"]}},"evmVersion":"paris","libraries":{}}},"imports":[],"versionRequirement":">=0.6.2, <0.9.0","artifacts":{"safeconsole":{"0.8.23+commit.f704f362.Darwin.appleclang":"safeconsole.sol/safeconsole.json"}}},"openzeppelin-contracts/contracts/token/ERC20/IERC20.sol":{"lastModificationDate":1703675472110,"contentHash":"ba5a9ac0e2191b28894cdf345e49fb43","sourceName":"openzeppelin-contracts/contracts/token/ERC20/IERC20.sol","solcConfig":{"settings":{"optimizer":{"enabled":true,"runs":200},"metadata":{"useLiteralContent":false,"bytecodeHash":"ipfs","appendCBOR":true},"outputSelection":{"*":{"":["ast"],"*":["abi","evm.bytecode","evm.deployedBytecode","evm.methodIdentifiers","metadata"]}},"evmVersion":"paris","libraries":{}}},"imports":[],"versionRequirement":"^0.8.20","artifacts":{"IERC20":{"0.8.23+commit.f704f362.Darwin.appleclang":"ERC20/IERC20.sol/IERC20.json"}}},"openzeppelin-contracts/contracts/token/ERC20/extensions/IERC20Permit.sol":{"lastModificationDate":1703675472111,"contentHash":"e944bb99ee63a3e1dec7b8f306b918ec","sourceName":"openzeppelin-contracts/contracts/token/ERC20/extensions/IERC20Permit.sol","solcConfig":{"settings":{"optimizer":{"enabled":true,"runs":200},"metadata":{"useLiteralContent":false,"bytecodeHash":"ipfs","appendCBOR":true},"outputSelection":{"*":{"":["ast"],"*":["abi","evm.bytecode","evm.deployedBytecode","evm.methodIdentifiers","metadata"]}},"evmVersion":"paris","libraries":{}}},"imports":[],"versionRequirement":"^0.8.20","artifacts":{"IERC20Permit":{"0.8.23+commit.f704f362.Darwin.appleclang":"extensions/IERC20Permit.sol/IERC20Permit.json"}}},"openzeppelin-contracts/contracts/token/ERC20/utils/SafeERC20.sol":{"lastModificationDate":1703675472111,"contentHash":"e102fc5a7612c107483121a952e71622","sourceName":"openzeppelin-contracts/contracts/token/ERC20/utils/SafeERC20.sol","solcConfig":{"settings":{"optimizer":{"enabled":true,"runs":200},"metadata":{"useLiteralContent":false,"bytecodeHash":"ipfs","appendCBOR":true},"outputSelection":{"*":{"":["ast"],"*":["abi","evm.bytecode","evm.deployedBytecode","evm.methodIdentifiers","metadata"]}},"evmVersion":"paris","libraries":{}}},"imports":["openzeppelin-contracts/contracts/token/ERC20/IERC20.sol","openzeppelin-contracts/contracts/token/ERC20/extensions/IERC20Permit.sol","openzeppelin-contracts/contracts/utils/Address.sol"],"versionRequirement":"^0.8.20","artifacts":{"SafeERC20":{"0.8.23+commit.f704f362.Darwin.appleclang":"utils/SafeERC20.sol/SafeERC20.json"}}},"openzeppelin-contracts/contracts/utils/Address.sol":{"lastModificationDate":1703675472113,"contentHash":"79c699f80eb8a9b168cb34e37816f894","sourceName":"openzeppelin-contracts/contracts/utils/Address.sol","solcConfig":{"settings":{"optimizer":{"enabled":true,"runs":200},"metadata":{"useLiteralContent":false,"bytecodeHash":"ipfs","appendCBOR":true},"outputSelection":{"*":{"":["ast"],"*":["abi","evm.bytecode","evm.deployedBytecode","evm.methodIdentifiers","metadata"]}},"evmVersion":"paris","libraries":{}}},"imports":[],"versionRequirement":"^0.8.20","artifacts":{"Address":{"0.8.23+commit.f704f362.Darwin.appleclang":"Address.sol/Address.json"}}}}}